bibelen/__init__.py
bibelen/bibelen.py
bibelen-0.1.4.dist-info/LICENSE
bibelen-0.1.4.dist-info/WHEEL
bibelen-0.1.4.dist-info/METADATA
bibelen-0.1.4.dist-info/RECORD
