Metadata-Version: 2.1
Name: bibelen
Version: 0.1.4
Summary: Scrape norwegian Bibles on Youversion website and generate a Logos compatible format
Author: Paul Mairo
Author-email: herrmpr@gmail.com
Requires-Python: >=3.10,<4.0
Classifier: Programming Language :: Python :: 3
Classifier: Programming Language :: Python :: 3.10
Requires-Dist: beautifulsoup4 (>=4.11.1,<5.0.0)
Requires-Dist: html5lib (>=1.1,<2.0)
Requires-Dist: requests (>=2.28.1,<3.0.0)
Requires-Dist: tqdm (>=4.64.1,<5.0.0)
